enviz/__init__.py
enviz/env.py
enviz-0.1.2.dist-info/LICENSE
enviz-0.1.2.dist-info/METADATA
enviz-0.1.2.dist-info/WHEEL
enviz-0.1.2.dist-info/top_level.txt
enviz-0.1.2.dist-info/RECORD
