Metadata-Version: 2.1
Name: enviz
Version: 0.1.2
Summary: Python .env file made easier
Author: oskvr37
Project-URL: Homepage, https://github.com/oskvr37/enviz
Classifier: Programming Language :: Python :: 3
Classifier: License :: OSI Approved :: MIT License
Classifier: Operating System :: OS Independent
Requires-Python: >=3.8
License-File: LICENSE
